{
    "Titles":[
        {
            "Left":514,"Top":86,
            "Rect":{"W":110,"H":100},
            "Option":{"Align":3,"Border":15,"Float":1},
            "Text":"设备管理中心确认签章\n年   月   日",
            "FontStyle":{"Name":"kai","Style":"","Size":10}
        },
        {
            "Left":24,"Top":60,
            "Rect":{"W":200,"H":25},
            "Option":{"Align":40,"Border":0,"Float":1},
            "Text":"派车单位",
            "FontStyle":{"Name":"kai","Style":"","Size":10}
        },
        {
            "Left":174,"Top":60,
            "Rect":{"W":300,"H":25},
            "Option":{"Align":48,"Border":0,"Float":1},
            "Text":"派车单位",
            "FontStyle":{"Name":"kai","Style":"","Size":10}
        },
        {
            "Left":424,"Top":60,
            "Rect":{"W":200,"H":25},
            "Option":{"Align":34,"Border":0,"Float":1},
            "Text":"派车单位",
            "FontStyle":{"Name":"kai","Style":"","Size":10}
        },
        {
            "Left":84,"Top":86,
            "Rect":{"W":100,"H":25},
            "Option":{"Align":48,"Border":15,"Float":1},
            "Text":"派车单位",
            "FontStyle":{"Name":"kai","Style":"","Size":10}
        },
        {
            "Left":244,"Top":86,
            "Rect":{"W":100,"H":25},
            "Option":{"Align":48,"Border":15,"Float":1},
            "Text":"派车单位",
            "FontStyle":{"Name":"kai","Style":"","Size":10}
        },
        {
            "Left":414,"Top":86,
            "Rect":{"W":100,"H":25},
            "Option":{"Align":48,"Border":15,"Float":1},
            "Text":"派车单位",
            "FontStyle":{"Name":"kai","Style":"","Size":10}
        }

    ],
    "Cells":[
        {
            "Left":24,"Top":10,
            "Rect":{"W":600,"H":60},
            "Option":{"Align":48,"Border":0,"Float":1},
            "Text":"广西金川公司汽车运输任务单",
            "FontStyle":{"Name":"kai","Style":"","Size":20}
        },
        {
            "Left":24,"Top":86,
            "Rect":{"W":60,"H":25},
            "Option":{"Align":48,"Border":15,"Float":1},
            "Text":"派车单位",
            "FontStyle":{"Name":"kai","Style":"","Size":10}
        },
        {
            "Left":184,"Top":86,
            "Rect":{"W":60,"H":25},
            "Option":{"Align":48,"Border":15,"Float":1},
            "Text":"车型吨位",
            "FontStyle":{"Name":"kai","Style":"","Size":10}
        },
        {
            "Left":344,"Top":86,
            "Rect":{"W":70,"H":25},
            "Option":{"Align":48,"Border":15,"Float":1},
            "Text":"车牌号",
            "FontStyle":{"Name":"kai","Style":"","Size":10}
        },
        {
            "Left":24,"Top":111,
            "Rect":{"W":220,"H":25},
            "Option":{"Align":48,"Border":15,"Float":1},
            "Text":"作业时段及内容",
            "FontStyle":{"Name":"kai","Style":"","Size":10}
        },
        {
            "Left":244,"Top":111,
            "Rect":{"W":100,"H":25},
            "Option":{"Align":48,"Border":15,"Float":1},
            "Text":"作业地点",
            "FontStyle":{"Name":"kai","Style":"","Size":10}
        },
        {
            "Left":344,"Top":111,
            "Rect":{"W":70,"H":25},
            "Option":{"Align":48,"Border":15,"Float":1},
            "Text":"作业量\n台班或吨位",
            "FontStyle":{"Name":"kai","Style":"","Size":10}
        },
        {
            "Left":414,"Top":111,
            "Rect":{"W":40,"H":25},
            "Option":{"Align":48,"Border":15,"Float":1},
            "Text":"单价",
            "FontStyle":{"Name":"kai","Style":"","Size":10}
        },
        {
            "Left":454,"Top":111,
            "Rect":{"W":60,"H":25},
            "Option":{"Align":48,"Border":15,"Float":1},
            "Text":"金额",
            "FontStyle":{"Name":"kai","Style":"","Size":10}
        },
        {
            "Left":24,"Top":136,
            "Rect":{"W":490,"H":25},
            "Option":{"Align":48,"Border":15,"Float":1},
            "Text":"",
            "FontStyle":{"Name":"kai","Style":"","Size":10}
        },
        {
            "Left":24,"Top":161,
            "Rect":{"W":490,"H":25},
            "Option":{"Align":48,"Border":15,"Float":1},
            "Text":"",
            "FontStyle":{"Name":"kai","Style":"","Size":10}
        },
        {
            "Left":24,"Top":186,
            "Rect":{"W":490,"H":25},
            "Option":{"Align":48,"Border":15,"Float":1},
            "Text":"",
            "FontStyle":{"Name":"kai","Style":"","Size":10}
        },
        {
            "Left":24,"Top":211,
            "Rect":{"W":490,"H":25},
            "Option":{"Align":48,"Border":15,"Float":1},
            "Text":"",
            "FontStyle":{"Name":"kai","Style":"","Size":10}
        },
        {
            "Left":24,"Top":236,
            "Rect":{"W":60,"H":25},
            "Option":{"Align":48,"Border":15,"Float":1},
            "Text":"备注",
            "FontStyle":{"Name":"kai","Style":"","Size":10}
        },
        {
            "Left":24,"Top":261,
            "Rect":{"W":390,"H":25},
            "Option":{"Align":40,"Border":15,"Float":1},
            "Text":"合计金额（大写）：",
            "FontStyle":{"Name":"kai","Style":"","Size":10}
        },
        {
            "Left":24,"Top":261,
            "Rect":{"W":390,"H":25},
            "Option":{"Align":34,"Border":0,"Float":1},
            "Text":"分",
            "FontStyle":{"Name":"kai","Style":"","Size":10}
        },
        {
            "Left":24,"Top":261,
            "Rect":{"W":355,"H":25},
            "Option":{"Align":34,"Border":0,"Float":1},
            "Text":"角",
            "FontStyle":{"Name":"kai","Style":"","Size":10}
        },
        {
            "Left":24,"Top":261,
            "Rect":{"W":320,"H":25},
            "Option":{"Align":34,"Border":0,"Float":1},
            "Text":"元",
            "FontStyle":{"Name":"kai","Style":"","Size":10}
        },
        {
            "Left":24,"Top":261,
            "Rect":{"W":285,"H":25},
            "Option":{"Align":34,"Border":0,"Float":1},
            "Text":"拾",
            "FontStyle":{"Name":"kai","Style":"","Size":10}
        },
        {
            "Left":24,"Top":261,
            "Rect":{"W":250,"H":25},
            "Option":{"Align":34,"Border":0,"Float":1},
            "Text":"佰",
            "FontStyle":{"Name":"kai","Style":"","Size":10}
        },
        {
            "Left":24,"Top":261,
            "Rect":{"W":215,"H":25},
            "Option":{"Align":34,"Border":0,"Float":1},
            "Text":"仟",
            "FontStyle":{"Name":"kai","Style":"","Size":10}
        },
        {
            "Left":24,"Top":261,
            "Rect":{"W":180,"H":25},
            "Option":{"Align":34,"Border":0,"Float":1},
            "Text":"万",
            "FontStyle":{"Name":"kai","Style":"","Size":10}
        },
        {
            "Left":24,"Top":261,
            "Rect":{"W":145,"H":25},
            "Option":{"Align":34,"Border":0,"Float":1},
            "Text":"拾",
            "FontStyle":{"Name":"kai","Style":"","Size":10}
        },
        {
            "Left":414,"Top":261,
            "Rect":{"W":100,"H":25},
            "Option":{"Align":40,"Border":15,"Float":1},
            "Text":"小写￥",
            "FontStyle":{"Name":"kai","Style":"","Size":10}
        },
        {
            "Left":414,"Top":261,
            "Rect":{"W":100,"H":25},
            "Option":{"Align":34,"Border":15,"Float":1},
            "Text":"元",
            "FontStyle":{"Name":"kai","Style":"","Size":10}
        },
        {
            "Left":244,"Top":136,
            "Rect":{"W":100,"H":100},
            "Option":{"Align":48,"Border":15,"Float":1},
            "Text":"",
            "FontStyle":{"Name":"kai","Style":"","Size":10}
        },
        {
            "Left":414,"Top":136,
            "Rect":{"W":40,"H":100},
            "Option":{"Align":48,"Border":15,"Float":1},
            "Text":"",
            "FontStyle":{"Name":"kai","Style":"","Size":10}
        },
        {
            "Left":514,"Top":186,
            "Rect":{"W":110,"H":100},
            "Option":{"Align":3,"Border":15,"Float":1},
            "Text":"物流中心确认签章\n年    月    日",
            "FontStyle":{"Name":"kai","Style":"","Size":10}
        },
        {
            "Left":24,"Top":290,
            "Rect":{"W":200,"H":25},
            "Option":{"Align":40,"Border":0,"Float":1},
            "Text":"用车单位负责人：",
            "FontStyle":{"Name":"kai","Style":"","Size":10}
        },
        {
            "Left":224,"Top":290,
            "Rect":{"W":200,"H":25},
            "Option":{"Align":40,"Border":0,"Float":1},
            "Text":"用车单位经办人：",
            "FontStyle":{"Name":"kai","Style":"","Size":10}
        },
        {
            "Left":424,"Top":290,
            "Rect":{"W":200,"H":25},
            "Option":{"Align":40,"Border":0,"Float":1},
            "Text":"物流中心调度员：",
            "FontStyle":{"Name":"kai","Style":"","Size":10}
        },
        {
            "Left":24,"Top":320,
            "Rect":{"W":600,"H":25},
            "Option":{"Align":48,"Border":0,"Float":1},
            "Text":"红色联：物流中心存查  黄色联：财务存查  红色联：生产运行部存查  绿色联：用车单位存查",
            "FontStyle":{"Name":"kai","Style":"","Size":9}
        }
    ],
    "Details":[
        {
            "Left":24,"Top":136,
            "Rect":{"W":220,"H":25},
            "Option":{"Align":40,"Border":0,"Float":1},
            "Text":"作业时段及内容",
            "FontStyle":{"Name":"kai","Style":"","Size":10}
        },
        {
            "Left":244,"Top":136,
            "Rect":{"W":100,"H":25},
            "Option":{"Align":48,"Border":0,"Float":1},
            "Text":"作业地点",
            "FontStyle":{"Name":"kai","Style":"","Size":10}
        },
        {
            "Left":344,"Top":136,
            "Rect":{"W":70,"H":25},
            "Option":{"Align":34,"Border":0,"Float":1},
            "Text":"作业量\n台班或吨位",
            "FontStyle":{"Name":"kai","Style":"","Size":10}
        }
    ]
}